debugmes/__init__.py
debugmes/debugmes.py
debugmes-0.1.dist-info/METADATA
debugmes-0.1.dist-info/WHEEL
debugmes-0.1.dist-info/top_level.txt
debugmes-0.1.dist-info/RECORD
