Metadata-Version: 2.4
Name: debugmes
Version: 0.1
Summary: A library for debug messages
Author-email: relyadev <relyadev@gmail.com>
Keywords: debug,messages,style
Classifier: Programming Language :: Python :: 3
Classifier: License :: OSI Approved :: MIT License
Classifier: Operating System :: OS Independent
Requires-Python: >=3.8
